{
    "frames": {
        "show-0": {
            "frame": { "x": 0, "y": 0, "w": 204, "h": 180 },
            "rotated": false,
            "trimmed": false,
            "spriteSourceSize": { "x": 0, "y": 0, "w": 204, "h": 180 },
            "sourceSize": { "w": 204, "h": 180 }
        },
        "lie-0": {
            "frame": { "x": 0, "y": 180, "w": 90, "h": 90 },
            "rotated": false,
            "trimmed": false,
            "spriteSourceSize": { "x": 0, "y": 55, "w": 90, "h": 90 },
            "sourceSize": { "w": 90, "h": 90 }
        },
        "lie-0-left": {
            "frame": { "x": 0, "y": 180, "w": 90, "h": 90 },
            "rotated": true,
            "trimmed": false,
            "spriteSourceSize": { "x": 0, "y": 55, "w": 90, "h": 90 },
            "sourceSize": { "w": 90, "h": 90 }
        },
        "throw-0": {
            "frame": { "x": 0, "y": 270, "w": 90, "h": 90 },
            "rotated": false,
            "trimmed": false,
            "spriteSourceSize": { "x": 0, "y": 55, "w": 90, "h": 90 },
            "sourceSize": { "w": 90, "h": 90 }
        },
        "throw-0-left": {
            "frame": { "x": 0, "y": 270, "w": 90, "h": 90 },
            "rotated": true,
            "trimmed": false,
            "spriteSourceSize": { "x": 0, "y": 55, "w": 90, "h": 90 },
            "sourceSize": { "w": 90, "h": 90 }
        }
    },
    "meta": {
        "app": "TexturePacker x.x.x",
        "version": "1.0",
        "image": "face.default.png",
        "name": "face.default",
        "format": "RGBA8888",
        "scale": "1"
    },
    "src": ["src/assets/img/equips/faces/face.default.png"],
    "animations": {
        "show": {
            "key": "show",
            "frames": [
                {
                    "frame": "show-0",
                    "duration": 1
                }
            ],
            "frameRate": 10,
            "repeat": -1
        },
        "lieRight": {
            "key": "lieRight",
            "frames": [
                {
                    "frame": "lie-0",
                    "duration": 1
                }
            ],
            "frameRate": 10,
            "repeat": -1
        },
        "lieLeft": {
            "key": "lieLeft",
            "frames": [
                {
                    "frame": "lie-0-left",
                    "duration": 1
                }
            ],
            "frameRate": 10,
            "repeat": -1
        },
        "throwRight": {
            "key": "throwRight",
            "frames": [
                {
                    "frame": "throw-0",
                    "duration": 1
                }
            ],
            "frameRate": 10,
            "repeat": 0
        },
        "throwLeft": {
            "key": "throwLeft",
            "frames": [
                {
                    "frame": "throw-0-left",
                    "duration": 1
                }
            ],
            "frameRate": 10,
            "repeat": 0
        },
        "crawlRight": {
            "key": "crawlRight",
            "frames": [
                {
                    "frame": "lie-0",
                    "duration": 1
                }
            ],
            "frameRate": 20,
            "repeat": -1
        },
        "crawlLeft": {
            "key": "crawlLeft",
            "frames": [
                {
                    "frame": "lie-0-left",
                    "duration": 1
                }
            ],
            "frameRate": 20,
            "repeat": -1
        }
    }
}
